{
    "eepyxr": {
        "cargoLocks": null,
        "date": "2025-03-09",
        "extract": null,
        "name": "eepyxr",
        "passthru": null,
        "pinned": false,
        "src": {
            "deepClone": false,
            "fetchSubmodules": false,
            "leaveDotGit": false,
            "name": null,
            "rev": "b826495d60b297d4a7a38c3c10203c919209fc3d",
            "sha256": "sha256-eDGIE/Mbc+52qAqjU+N5yrR23BO7PXLJTsZFG66qoqE=",
            "sparseCheckout": [],
            "type": "git",
            "url": "https://github.com/Beyley/eepyxr.git"
        },
        "version": "b826495d60b297d4a7a38c3c10203c919209fc3d"
    },
    "envision-unwrapped": {
        "cargoLocks": {
            "Cargo.lock": [
                "./envision-unwrapped-754395586e8c690343d9826b437dd0a98a34b154/Cargo.lock",
                {}
            ]
        },
        "date": "2025-06-12",
        "extract": null,
        "name": "envision-unwrapped",
        "passthru": null,
        "pinned": false,
        "src": {
            "deepClone": false,
            "fetchSubmodules": false,
            "leaveDotGit": false,
            "name": null,
            "rev": "754395586e8c690343d9826b437dd0a98a34b154",
            "sha256": "sha256-4d9iI083wdVB2J+lmzPyIP5WjTnBggPeblDm+t2IFPs=",
            "sparseCheckout": [],
            "type": "git",
            "url": "https://gitlab.com/gabmus/envision.git"
        },
        "version": "754395586e8c690343d9826b437dd0a98a34b154"
    },
    "index_camera_passthrough": {
        "cargoLocks": {
            "Cargo.lock": [
                "./index_camera_passthrough-0d3ec30c5cd74e4a3df93d704ecf4a25136afd73/Cargo.lock",
                {
                    "vulkano-0.34.0": "sha256-co2+rDJ1jOee36x9FcLX2Pze9ZItBYHq9/pEq0NhcpY="
                }
            ]
        },
        "date": "2024-07-25",
        "extract": null,
        "name": "index_camera_passthrough",
        "passthru": null,
        "pinned": false,
        "src": {
            "deepClone": false,
            "fetchSubmodules": false,
            "leaveDotGit": false,
            "name": null,
            "rev": "0d3ec30c5cd74e4a3df93d704ecf4a25136afd73",
            "sha256": "sha256-jldpVWnpWEA3bi3lzmG94uCaoZuL+xhaEAtFiZrSGc4=",
            "sparseCheckout": [],
            "type": "git",
            "url": "https://github.com/yshui/index_camera_passthrough.git"
        },
        "version": "0d3ec30c5cd74e4a3df93d704ecf4a25136afd73"
    },
    "monado": {
        "cargoLocks": null,
        "date": "2025-06-09",
        "extract": null,
        "name": "monado",
        "passthru": null,
        "pinned": false,
        "src": {
            "deepClone": false,
            "fetchSubmodules": false,
            "leaveDotGit": false,
            "name": null,
            "rev": "d2ec236e3b77682cb97c9511983dccfe05db94ca",
            "sha256": "sha256-nLpbFUXLvLmAQDDQw1pPfsYRyRQH0y9mkhRByB2qdvw=",
            "sparseCheckout": [],
            "type": "git",
            "url": "https://gitlab.freedesktop.org/monado/monado.git"
        },
        "version": "d2ec236e3b77682cb97c9511983dccfe05db94ca"
    },
    "opencomposite": {
        "cargoLocks": null,
        "date": "2025-05-20",
        "extract": null,
        "name": "opencomposite",
        "passthru": null,
        "pinned": false,
        "src": {
            "deepClone": false,
            "fetchSubmodules": true,
            "leaveDotGit": false,
            "name": null,
            "rev": "8d43dc81dc31722dc2460fa21a21c6e18be0b2b4",
            "sha256": "sha256-hM+xsokPt4B27C7NdOfiEdEoQVnx4BpwybisuHf//uI=",
            "sparseCheckout": [],
            "type": "git",
            "url": "https://gitlab.com/znixian/OpenOVR.git"
        },
        "version": "8d43dc81dc31722dc2460fa21a21c6e18be0b2b4"
    },
    "vapor": {
        "cargoLocks": null,
        "date": "2025-05-27",
        "extract": null,
        "name": "vapor",
        "passthru": null,
        "pinned": false,
        "src": {
            "deepClone": false,
            "fetchSubmodules": false,
            "leaveDotGit": false,
            "name": null,
            "rev": "6d273cb6c7db0847daee1276be20886e6ff515ae",
            "sha256": "sha256-Ul7TBMyWnvsEIdaA0gEKiB5SNoiOSrcF937lkuZPUEg=",
            "sparseCheckout": [],
            "type": "git",
            "url": "https://github.com/micheal65536/VapoR.git"
        },
        "version": "6d273cb6c7db0847daee1276be20886e6ff515ae"
    },
    "wayvr-dashboard": {
        "cargoLocks": {
            "src-tauri/Cargo.lock": [
                "./wayvr-dashboard-02bc455ce9ffdb42fa3fd5cd86a750278436ad8c/src-tauri/Cargo.lock",
                {
                    "keyvalues-parser-0.2.0": "sha256-LT+WHhan/USzW0EOiuIBPG5j1r9qL4n7Z7ESDxO1xQQ=",
                    "libmonado-1.3.1": "sha256-HYYfpYhyo5VmbUdwMTJuAR+2dnMITIGZIPGX9Qsnc/g=",
                    "wayvr_ipc-0.1.0": "sha256-ieQaY08Ogl/F3t/p825LBp1lAO3SWH1F8206IPXEgTc="
                }
            ]
        },
        "date": "2025-06-08",
        "extract": null,
        "name": "wayvr-dashboard",
        "passthru": null,
        "pinned": false,
        "src": {
            "deepClone": false,
            "fetchSubmodules": false,
            "leaveDotGit": false,
            "name": null,
            "rev": "02bc455ce9ffdb42fa3fd5cd86a750278436ad8c",
            "sha256": "sha256-rDx8j/eoro3IKcgLEiM3y/Pe3jcBfOHKyNjhVVIWkjg=",
            "sparseCheckout": [],
            "type": "git",
            "url": "https://github.com/olekolek1000/wayvr-dashboard"
        },
        "version": "02bc455ce9ffdb42fa3fd5cd86a750278436ad8c"
    },
    "wivrn": {
        "cargoLocks": null,
        "date": "2025-06-13",
        "extract": null,
        "name": "wivrn",
        "passthru": null,
        "pinned": false,
        "src": {
            "deepClone": false,
            "fetchSubmodules": false,
            "leaveDotGit": false,
            "name": null,
            "owner": "WiVRn",
            "repo": "WiVRn",
            "rev": "2ee0604ccf5909a890366616f870808278db003c",
            "sha256": "sha256-zZvDAdLcd5uwU6NXkCE3wasmnWihrIXhQCoR41KDL+U=",
            "sparseCheckout": [],
            "type": "github"
        },
        "version": "2ee0604ccf5909a890366616f870808278db003c"
    },
    "wivrn-monado": {
        "cargoLocks": null,
        "date": null,
        "extract": null,
        "name": "wivrn-monado",
        "passthru": null,
        "pinned": false,
        "src": {
            "deepClone": false,
            "fetchSubmodules": false,
            "leaveDotGit": false,
            "name": null,
            "rev": "bb9bcee2a3be75592de819d9e3fb2c8ed27bb7dc",
            "sha256": "sha256-+PiWxnvMXaSFc+67r17GBRXo7kbjikSElawNMJCydrk=",
            "sparseCheckout": [],
            "type": "git",
            "url": "https://gitlab.freedesktop.org/monado/monado.git"
        },
        "version": "bb9bcee2a3be75592de819d9e3fb2c8ed27bb7dc"
    },
    "wlx-overlay-s": {
        "cargoLocks": {
            "Cargo.lock": [
                "./wlx-overlay-s-37bb0bb281b6db94da9433df72c920b4e5a4b9db/Cargo.lock",
                {
                    "libspa-0.8.0": "sha256-Gub2F/Gwia8DjFqUsM8e4Yr2ff92AwrWrszsws3X3sM=",
                    "openxr-0.19.0": "sha256-mljVBbQTq/k7zd/WcE1Sd3gibaJiZ+t7td964clWHd8=",
                    "ovr_overlay-0.0.0": "sha256-NHzESKsghqI98pkQxEmcNkQ9lTfBsqR9/25msbryi6E=",
                    "wayvr_ipc-0.1.0": "sha256-ieQaY08Ogl/F3t/p825LBp1lAO3SWH1F8206IPXEgTc=",
                    "wlx-capture-0.5.3": "sha256-1R5R9a9MSCWZ+S8GXu2oMBodoy9CCmCfAwH1eXBPqno="
                }
            ]
        },
        "date": "2025-06-08",
        "extract": null,
        "name": "wlx-overlay-s",
        "passthru": null,
        "pinned": false,
        "src": {
            "deepClone": false,
            "fetchSubmodules": false,
            "leaveDotGit": false,
            "name": null,
            "rev": "37bb0bb281b6db94da9433df72c920b4e5a4b9db",
            "sha256": "sha256-qoDcvEt9sWBey9dF44u+oVdcgBj+6Ldr/6sbhhb9t3E=",
            "sparseCheckout": [],
            "type": "git",
            "url": "https://github.com/galister/wlx-overlay-s.git"
        },
        "version": "37bb0bb281b6db94da9433df72c920b4e5a4b9db"
    },
    "xrizer": {
        "cargoLocks": {
            "Cargo.lock": [
                "./xrizer-898d41051d33f9404ea9a9e599f0c1118c82cc54/Cargo.lock",
                {
                    "openxr-0.19.0": "sha256-mljVBbQTq/k7zd/WcE1Sd3gibaJiZ+t7td964clWHd8="
                }
            ]
        },
        "date": "2025-06-08",
        "extract": null,
        "name": "xrizer",
        "passthru": null,
        "pinned": false,
        "src": {
            "deepClone": false,
            "fetchSubmodules": false,
            "leaveDotGit": false,
            "name": null,
            "rev": "898d41051d33f9404ea9a9e599f0c1118c82cc54",
            "sha256": "sha256-quCljMhsx1sy385NgQl6oPuJe44CuyoO3FWcmS005Wk=",
            "sparseCheckout": [],
            "type": "git",
            "url": "https://github.com/Supreeeme/xrizer.git"
        },
        "version": "898d41051d33f9404ea9a9e599f0c1118c82cc54"
    }
}